lesscode_tag/__init__.py
lesscode_tag/business.py
lesscode_tag/version.py
lesscode_tag-0.0.24.dist-info/METADATA
lesscode_tag-0.0.24.dist-info/WHEEL
lesscode_tag-0.0.24.dist-info/top_level.txt
lesscode_tag-0.0.24.dist-info/RECORD
