Metadata-Version: 2.1
Name: lesscode-tag
Version: 0.0.24
Summary: lesscode_tag是标签处理工具包
Author: Chao.yy
Author-email: yuyc@ishangqi.com
Platform: python
Classifier: Programming Language :: Python :: 3
Classifier: Operating System :: OS Independent
Requires-Python: >=3.6
Requires-Dist: lesscode-utils (>=0.0.1)
